nest/__init__.py
nest/controller.py
fastapi_nest-0.1.1.dist-info/METADATA
fastapi_nest-0.1.1.dist-info/WHEEL
fastapi_nest-0.1.1.dist-info/top_level.txt
fastapi_nest-0.1.1.dist-info/RECORD
