Metadata-Version: 2.1
Name: fastapi-nest
Version: 0.1.1
Summary: class base view for fastapi
Author-email: eatmoreapple <eatmoreorange@gmail.com>
Project-URL: homepage, https://github.com/eatmoreapple/fastapi-nest
Project-URL: documentation, https://github.com/eatmoreapple/fastapi-nest#readme
Project-URL: repository, https://github.com/eatmoreapple/fastapi-nest
Project-URL: issues, https://github.com/eatmoreapple/fastapi-nest/issues
Requires-Dist: fastapi
